cvmodels/__init__.py
cvmodels/cvmodels.py
cvmodels-0.0.0.0.1.dist-info/LICENSE
cvmodels-0.0.0.0.1.dist-info/METADATA
cvmodels-0.0.0.0.1.dist-info/WHEEL
cvmodels-0.0.0.0.1.dist-info/top_level.txt
cvmodels-0.0.0.0.1.dist-info/RECORD
