Metadata-Version: 2.1
Name: cvmodels
Version: 0.0.0.0.1
Summary: UNKNOWN
Home-page: https://github.com/ShaonMajumder/cvmodels
Author: Shaon Majumder
Author-email: smazoomder@gmail.com
License: UNKNOWN
Download-URL: https://github.com/ShaonMajumder/cvmodels/archive/0.0.0.0.1.tar.gz
Keywords: shaon,cvmodels,computer vision,deep learning,machine learning
Platform: UNKNOWN
